ioclib/falcon/__init__.py
ioclib/falcon/falcon.py
ioclib/tests/test_plugin_falcon.py
ioclib_falcon-1.4.dist-info/METADATA
ioclib_falcon-1.4.dist-info/WHEEL
ioclib_falcon-1.4.dist-info/top_level.txt
ioclib_falcon-1.4.dist-info/RECORD
